README.rst
setup.py
imgtools/__init__.py
imgtools/combining_png.py
imgtools/combining_svg.py
imgtools/same_size_svg.py
imgtools/svg.py
imgtools/version.py
imgtools.egg-info/PKG-INFO
imgtools.egg-info/SOURCES.txt
imgtools.egg-info/dependency_links.txt
imgtools.egg-info/entry_points.txt
imgtools.egg-info/requires.txt
imgtools.egg-info/top_level.txt